sqloxide_fork-0.1.51.dist-info/METADATA
sqloxide_fork-0.1.51.dist-info/WHEEL
sqloxide_fork-0.1.51.dist-info/licenses/LICENSE
sqloxide_fork/__init__.py
sqloxide_fork/sqloxide_fork.cpython-39-aarch64-linux-gnu.so
sqloxide_fork-0.1.51.dist-info/RECORD
