Metadata-Version: 2.3
Name: sqloxide_fork
Version: 0.1.51
Classifier: Programming Language :: Rust
License-File: LICENSE
Author: Will Eaton <me@wseaton.com>
Author-email: Will Eaton <me@wseaton.com>
Requires-Python: >=3.7
